{
	"info": {
		"_postman_id": "laravel-microservices-boilerplate",
		"name": "Laravel Microservices Boilerplate",
		"description": "API collection for Laravel Microservices Boilerplate",
		"schema": "https://schema.getpostman.com/json/collection/v2.1.0/collection.json"
	},
	"item": [
		{
			"name": "Health Check",
			"item": [
				{
					"name": "Get Health Status",
					"request": {
						"method": "GET",
						"header": [],
						"url": {
							"raw": "{{base_url}}/api/health",
							"host": [
								"{{base_url}}"
							],
							"path": [
								"api",
								"health"
							]
						},
						"description": "Check if the API is running and healthy"
					},
					"response": [
						{
							"name": "Success",
							"originalRequest": {
								"method": "GET",
								"header": [],
								"url": {
									"raw": "{{base_url}}/api/health",
									"host": [
										"{{base_url}}"
									],
									"path": [
										"api",
										"health"
									]
								}
							},
							"status": "OK",
							"code": 200,
							"_postman_previewlanguage": "json",
							"header": [
								{
									"key": "Content-Type",
									"value": "application/json"
								}
							],
							"cookie": [],
							"body": "{\n    \"status\": \"ok\",\n    \"service\": \"Laravel\",\n    \"timestamp\": \"2024-01-01T00:00:00+00:00\",\n    \"environment\": \"local\"\n}"
						}
					]
				}
			],
			"description": "Health check endpoints"
		}
	],
	"event": [
		{
			"listen": "prerequest",
			"script": {
				"type": "text/javascript",
				"exec": [
					""
				]
			}
		},
		{
			"listen": "test",
			"script": {
				"type": "text/javascript",
				"exec": [
					""
				]
			}
		}
	],
	"variable": [
		{
			"key": "base_url",
			"value": "http://localhost:8000",
			"type": "string"
		},
		{
			"key": "token",
			"value": "",
			"type": "string"
		},
		{
			"key": "api_key",
			"value": "",
			"type": "string"
		}
	]
}

